hyperopt_prophet/__init__.py
hyperopt_prophet/inference.py
hyperopt_prophet/model.py
hyperopt_prophet/training.py
hyperopt_prophet/utils.py
main.py
hyperopt_prophet-0.2.4.dist-info/LICENSE
hyperopt_prophet-0.2.4.dist-info/METADATA
hyperopt_prophet-0.2.4.dist-info/WHEEL
hyperopt_prophet-0.2.4.dist-info/entry_points.txt
hyperopt_prophet-0.2.4.dist-info/RECORD
