Metadata-Version: 2.1
Name: hyperopt-prophet
Version: 0.2.4
Summary: Integration of prophet forecasting with hyperopt, mlflow
License: MIT
Author: Carlos D. Escobar-Valbuena
Author-email: carlosdavidescobar@gmail.com
Requires-Python: >=3.8,<4.0
Classifier: License :: OSI Approved :: MIT License
Classifier: Programming Language :: Python :: 3
Classifier: Programming Language :: Python :: 3.8
Classifier: Programming Language :: Python :: 3.9
Classifier: Programming Language :: Python :: 3.10
Classifier: Programming Language :: Python :: 3.11
Requires-Dist: cloudpickle (>=2.2.1,<3.0.0)
Requires-Dist: cython (>=3.0.0,<4.0.0)
Requires-Dist: holidays (==0.24)
Requires-Dist: hyperopt (==0.2.7)
Requires-Dist: mlflow (==2.5.0)
Requires-Dist: mlflowops (>=0.1.2,<0.2.0)
Requires-Dist: nbformat (>=5.9.1,<6.0.0)
Requires-Dist: pandas (>=2.0.3,<3.0.0)
Requires-Dist: plotly (==5.15.0)
Requires-Dist: prophet (==1.1.1)
Requires-Dist: pydantic (>=2.1.0,<3.0.0)
